{
  "version": "7",
  "dialect": "postgresql",
  "entries": [
    {
      "idx": 0,
      "version": "7",
      "when": 1783425298774,
      "tag": "0000_conscious_red_shift",
      "breakpoints": true
    },
    {
      "idx": 1,
      "version": "7",
      "when": 1783427596590,
      "tag": "0001_silly_lord_tyger",
      "breakpoints": true
    },
    {
      "idx": 2,
      "version": "7",
      "when": 1783448335107,
      "tag": "0002_worried_may_parker",
      "breakpoints": true
    },
    {
      "idx": 3,
      "version": "7",
      "when": 1783457347128,
      "tag": "0003_melodic_firestar",
      "breakpoints": true
    },
    {
      "idx": 4,
      "version": "7",
      "when": 1783467345626,
      "tag": "0004_zippy_eddie_brock",
      "breakpoints": true
    },
    {
      "idx": 5,
      "version": "7",
      "when": 1783636424256,
      "tag": "0005_optimal_nighthawk",
      "breakpoints": true
    },
    {
      "idx": 6,
      "version": "7",
      "when": 1783645473039,
      "tag": "0006_ambitious_jean_grey",
      "breakpoints": true
    },
    {
      "idx": 7,
      "version": "7",
      "when": 1783804972101,
      "tag": "0007_spotty_risque",
      "breakpoints": true
    }
  ]
}